featuretools_sklearn_transformer/__init__.py
featuretools_sklearn_transformer/transformer.py
featuretools_sklearn_transformer/tests/__init__.py
featuretools_sklearn_transformer/tests/test_transformer.py
featuretools_sklearn_transformer-1.0.0.dist-info/LICENSE
featuretools_sklearn_transformer-1.0.0.dist-info/METADATA
featuretools_sklearn_transformer-1.0.0.dist-info/WHEEL
featuretools_sklearn_transformer-1.0.0.dist-info/entry_points.txt
featuretools_sklearn_transformer-1.0.0.dist-info/top_level.txt
featuretools_sklearn_transformer-1.0.0.dist-info/RECORD
