Metadata-Version: 2.1
Name: featuretools-sklearn-transformer
Version: 1.0.0
Summary: Featuretools Transformer for Scikit-Learn Pipeline use.
Home-page: http://www.featurelabs.com/
Author: Feature Labs, Inc.
Author-email: support@featurelabs.com
License: BSD 3-clause
Platform: UNKNOWN
Requires-Python: >=3.7, <4
License-File: LICENSE
Requires-Dist: featuretools (>=1.0.0)
Requires-Dist: numpy
Requires-Dist: pandas
Requires-Dist: scikit-learn (!=0.22,>=0.20.0)
